<repast.simphony.data2.engine.DataSetDescriptor>
  <name>A Data Set</name>
  <type>AGGREGATE</type>
  <inclTick>true</inclTick>
  <inclBatchRun>false</inclBatchRun>
  <inclRandomSeed>false</inclRandomSeed>
  <scheduleParams>
    <start>1.0</start>
    <interval>1.0</interval>
    <priority>-Infinity</priority>
    <pType>LAST</pType>
    <duration>-1.0</duration>
    <frequency>REPEAT</frequency>
    <hashCode>-1769143506</hashCode>
  </scheduleParams>
  <atEnd>false</atEnd>
  <methodDataSources class="linked-hash-map">
    <entry>
      <string>IctSerNo</string>
      <repast.simphony.data2.engine.MethodDataSourceDefinition>
        <id>IctSerNo</id>
        <className>solarPanelAdoption.Updater</className>
        <methodName>getSerNo</methodName>
        <aggType>MEAN</aggType>
      </repast.simphony.data2.engine.MethodDataSourceDefinition>
    </entry>
    <entry>
      <string>systemCost</string>
      <repast.simphony.data2.engine.MethodDataSourceDefinition>
        <id>systemCost</id>
        <className>solarPanelAdoption.NonAdopter</className>
        <methodName>getCost</methodName>
        <aggType>MEAN</aggType>
      </repast.simphony.data2.engine.MethodDataSourceDefinition>
    </entry>
    <entry>
      <string>incentive</string>
      <repast.simphony.data2.engine.MethodDataSourceDefinition>
        <id>incentive</id>
        <className>solarPanelAdoption.NonAdopter</className>
        <methodName>getIncentive</methodName>
        <aggType>MEAN</aggType>
      </repast.simphony.data2.engine.MethodDataSourceDefinition>
    </entry>
    <entry>
      <string>netSysCost</string>
      <repast.simphony.data2.engine.MethodDataSourceDefinition>
        <id>netSysCost</id>
        <className>solarPanelAdoption.NonAdopter</className>
        <methodName>getNetCost</methodName>
        <aggType>MEAN</aggType>
      </repast.simphony.data2.engine.MethodDataSourceDefinition>
    </entry>
    <entry>
      <string>deviance</string>
      <repast.simphony.data2.engine.MethodDataSourceDefinition>
        <id>deviance</id>
        <className>solarPanelAdoption.Updater</className>
        <methodName>getDeviance</methodName>
        <aggType>MEAN</aggType>
      </repast.simphony.data2.engine.MethodDataSourceDefinition>
    </entry>
    <entry>
      <string>realAdopt</string>
      <repast.simphony.data2.engine.MethodDataSourceDefinition>
        <id>realAdopt</id>
        <className>solarPanelAdoption.Updater</className>
        <methodName>getRealPath</methodName>
        <aggType>MEAN</aggType>
      </repast.simphony.data2.engine.MethodDataSourceDefinition>
    </entry>
    <entry>
      <string>remainBgt</string>
      <repast.simphony.data2.engine.MethodDataSourceDefinition>
        <id>remainBgt</id>
        <className>solarPanelAdoption.UpdaterAveStep</className>
        <methodName>getRemainBudget</methodName>
        <aggType>MEAN</aggType>
      </repast.simphony.data2.engine.MethodDataSourceDefinition>
    </entry>
    <entry>
      <string>seeded</string>
      <repast.simphony.data2.engine.MethodDataSourceDefinition>
        <id>seeded</id>
        <className>solarPanelAdoption.HouseHold</className>
        <methodName>getSeeded</methodName>
        <aggType>SUM</aggType>
      </repast.simphony.data2.engine.MethodDataSourceDefinition>
    </entry>
    <entry>
      <string>numAdopt</string>
      <repast.simphony.data2.engine.MethodDataSourceDefinition>
        <id>numAdopt</id>
        <className>solarPanelAdoption.Adopter</className>
        <methodName>getCount</methodName>
        <aggType>SUM</aggType>
      </repast.simphony.data2.engine.MethodDataSourceDefinition>
    </entry>
    <entry>
      <string>step</string>
      <repast.simphony.data2.engine.MethodDataSourceDefinition>
        <id>step</id>
        <className>solarPanelAdoption.Updater</className>
        <methodName>getStep</methodName>
        <aggType>MEAN</aggType>
      </repast.simphony.data2.engine.MethodDataSourceDefinition>
    </entry>
    <entry>
      <string>rate</string>
      <repast.simphony.data2.engine.MethodDataSourceDefinition>
        <id>rate</id>
        <className>solarPanelAdoption.Updater</className>
        <methodName>getRate</methodName>
        <aggType>MEAN</aggType>
      </repast.simphony.data2.engine.MethodDataSourceDefinition>
    </entry>
    <entry>
      <string>mwSD</string>
      <repast.simphony.data2.engine.MethodDataSourceDefinition>
        <id>mwSD</id>
        <className>solarPanelAdoption.Updater</className>
        <methodName>getTotalMegawatt</methodName>
        <aggType>MEAN</aggType>
      </repast.simphony.data2.engine.MethodDataSourceDefinition>
    </entry>
    <entry>
      <string>captured</string>
      <repast.simphony.data2.engine.MethodDataSourceDefinition>
        <id>captured</id>
        <className>solarPanelAdoption.HouseHold</className>
        <methodName>getCaptured</methodName>
        <aggType>SUM</aggType>
      </repast.simphony.data2.engine.MethodDataSourceDefinition>
    </entry>
    <entry>
      <string>realStep</string>
      <repast.simphony.data2.engine.MethodDataSourceDefinition>
        <id>realStep</id>
        <className>solarPanelAdoption.Updater</className>
        <methodName>getRealStep</methodName>
        <aggType>MEAN</aggType>
      </repast.simphony.data2.engine.MethodDataSourceDefinition>
    </entry>
    <entry>
      <string>nullDev</string>
      <repast.simphony.data2.engine.MethodDataSourceDefinition>
        <id>nullDev</id>
        <className>solarPanelAdoption.Updater</className>
        <methodName>getNullDeviance</methodName>
        <aggType>MEAN</aggType>
      </repast.simphony.data2.engine.MethodDataSourceDefinition>
    </entry>
    <entry>
      <string>npvOwn</string>
      <repast.simphony.data2.engine.MethodDataSourceDefinition>
        <id>npvOwn</id>
        <className>solarPanelAdoption.NonAdopter</className>
        <methodName>getNPVown</methodName>
        <aggType>MEAN</aggType>
      </repast.simphony.data2.engine.MethodDataSourceDefinition>
    </entry>
    <entry>
      <string>npvLease</string>
      <repast.simphony.data2.engine.MethodDataSourceDefinition>
        <id>npvLease</id>
        <className>solarPanelAdoption.NonAdopter</className>
        <methodName>getNPVlease</methodName>
        <aggType>MEAN</aggType>
      </repast.simphony.data2.engine.MethodDataSourceDefinition>
    </entry>
  </methodDataSources>
  <countSources class="linked-hash-map"/>
  <customNADataSources class="linked-hash-map"/>
  <customAggDataSources class="linked-hash-map"/>
</repast.simphony.data2.engine.DataSetDescriptor>